{
  "allyCode": 286981522,
  "name": "Maki",
  "guildRefId": "G810398809",
  "roster": [
    {
      "defId": "ZEBS3",
      "nameKey": "Garazeb \"Zeb\" Orrelios",
      "rarity": 6,
      "level": 85,
      "gear": 8,
      "skills": [
        {
          "isZeta": true
        },
        {
          "isZeta": false
        },
        {
          "isZeta": false
        },
        {
          "isZeta": false
        }
      ],
      "gp": 8281,
      "relic": {
        "currentTier": 1
      }
    },
    {
      "defId": "DARTHREVAN",
      "nameKey": "Darth Revan",
      "rarity": 7,
      "level": 85,
      "gear": 13,
      "skills": [
        {
          "isZeta": false
        },
        {
          "isZeta": false
        },
        {
          "isZeta": false
        },
        {
          "isZeta": true
        },
        {
          "isZeta": true
        },
        {
          "isZeta": true
        }
      ],
      "gp": 27438,
      "relic": {
        "currentTier": 9
      }
    },
    {
      "defId": "R2D2_LEGENDARY",
      "nameKey": "R2-D2",
      "rarity": 5,
      "level": 40,
      "gear": 5,
      "skills": [
        {
          "isZeta": false
        },
        {
          "isZeta": false
        },
        {
          "isZeta": false
        },
        {
          "isZeta": true
        }
      ],
      "gp": 2946,
      "relic": {
        "currentTier": 1
      }
    },
    {
      "defId": "CT210408",
      "nameKey": "CT-21-0408 \"Echo\"",
      "rarity": 7,
      "level": 85,
      "gear": 11,
      "skills": [
        {
          "isZeta": false
        },
        {
          "isZeta": true
        },
        {
          "isZeta": false
        },
        {
          "isZeta": false
        }
      ],
      "gp": 17011,
      "relic": {
        "currentTier": 1
      }
    },
    {
      "defId": "B1BATTLEDROIDV2",
      "nameKey": "B1 Battle Droid",
      "rarity": 7,
      "level": 85,
      "gear": 12,
      "skills": [
        {
          "isZeta": true
        },
        {
          "isZeta": false
        },
        {
          "isZeta": false
        },
        {
          "isZeta": false
        }
      ],
      "gp": 20478,
      "relic": {
        "currentTier": 1
      }
    },
    {
      "defId": "BB8",
      "nameKey": "BB-8",
      "rarity": 5,
      "level": 1,
      "gear": 1,
      "skills": [],
      "gp": 1521,
      "relic": {
        "currentTier": 1
      }
    },
    {
      "defId": "POGGLETHELESSER",
      "nameKey": "Poggle the Lesser",
      "rarity": 7,
      "level": 85,
      "gear": 12,
      "skills": [
        {
          "isZeta": false
        },
        {
          "isZeta": false
        },
        {
          "isZeta": false
        },
        {
          "isZeta": false
        }
      ],
      "gp": 17952,
      "relic": {
        "currentTier": 1
      }
    },
    {
      "defId": "GENERALKENOBI",
      "nameKey": "General Kenobi",
      "rarity": 7,
      "level": 85,
      "gear": 9,
      "skills": [
        {
          "isZeta": false
        },
        {
          "isZeta": false
        },
        {
          "isZeta": false
        },
        {
          "isZeta": false
        },
        {
          "isZeta": true
        }
      ],
      "gp": 17748,
      "relic": {
        "currentTier": 1
      }
    },
    {
      "defId": "MOTHERTALZIN",
      "nameKey": "Mother Talzin",
      "rarity": 7,
      "level": 85,
      "gear": 13,
      "skills": [
        {
          "isZeta": false
        },
        {
          "isZeta": false
        },
        {
          "isZeta": false
        },
        {
          "isZeta": true
        },
        {
          "isZeta": true
        }
      ],
      "gp": 24154,
      "relic": {
        "currentTier": 6
      }
    },
    {
      "defId": "DROIDEKA",
      "nameKey": "Droideka",
      "rarity": 7,
      "level": 85,
      "gear": 12,
      "skills": [
        {
          "isZeta": false
        },
        {
          "isZeta": false
        },
        {
          "isZeta": false
        },
        {
          "isZeta": true
        }
      ],
      "gp": 17859,
      "relic": {
        "currentTier": 1
      }
    },
    {
      "defId": "BIGGSDARKLIGHTER",
      "nameKey": "Biggs Darklighter",
      "rarity": 7,
      "level": 85,
      "gear": 8,
      "skills": [
        {
          "isZeta": false
        },
        {
          "isZeta": false
        },
        {
          "isZeta": false
        }
      ],
      "gp": 12727,
      "relic": {
        "currentTier": 1
      }
    },
    {
      "defId": "CC2224",
      "nameKey": "CC-2224 \"Cody\"",
      "rarity": 5,
      "level": 80,
      "gear": 8,
      "skills": [
        {
          "isZeta": false
        },
        {
          "isZeta": false
        },
        {
          "isZeta": true
        },
        {
          "isZeta": false
        }
      ],
      "gp": 7483,
      "relic": {
        "currentTier": 1
      }
    },
    {
      "defId": "C3POLEGENDARY",
      "nameKey": "C-3PO",
      "rarity": 7,
      "level": 85,
      "gear": 8,
      "skills": [
        {
          "isZeta": false
        },
        {
          "isZeta": true
        },
        {
          "isZeta": false
        },
        {
          "isZeta": true
        },
        {
          "isZeta": false
        },
        {
          "isZeta": false
        },
        {
          "isZeta": false
        }
      ],
      "gp": 15607,
      "relic": {
        "currentTier": 1
      }
    },
    {
      "defId": "EWOKSCOUT",
      "nameKey": "Ewok Scout",
      "rarity": 1,
      "level": 30,
      "gear": 4,
      "skills": [],
      "gp": 1194,
      "relic": {
        "currentTier": 1
      }
    },
    {
      "defId": "JEDIKNIGHTREVAN",
      "nameKey": "Jedi Knight Revan",
      "rarity": 7,
      "level": 85,
      "gear": 13,
      "skills": [
        {
          "isZeta": false
        },
        {
          "isZeta": false
        },
        {
          "isZeta": true
        },
        {
          "isZeta": true
        },
        {
          "isZeta": false
        },
        {
          "isZeta": true
        }
      ],
      "gp": 24796,
      "relic": {
        "currentTier": 9
      }
    },
    {
      "defId": "PADMEAMIDALA",
      "nameKey": "Padmé Amidala",
      "rarity": 7,
      "level": 85,
      "gear": 13,
      "skills": [
        {
          "isZeta": false
        },
        {
          "isZeta": false
        },
        {
          "isZeta": false
        },
        {
          "isZeta": true
        },
        {
          "isZeta": true
        }
      ],
      "gp": 24108,
      "relic": {
        "currentTier": 6
      }
    },
    {
      "defId": "K2SO",
      "nameKey": "K-2SO",
      "rarity": 5,
      "level": 80,
      "gear": 8,
      "skills": [
        {
          "isZeta": false
        },
        {
          "isZeta": false
        },
        {
          "isZeta": false
        },
        {
          "isZeta": true
        }
      ],
      "gp": 6577,
      "relic": {
        "currentTier": 1
      }
    },
    {
      "defId": "CT7567",
      "nameKey": "CT-7567 \"Rex\"",
      "rarity": 7,
      "level": 85,
      "gear": 12,
      "skills": [
        {
          "isZeta": false
        },
        {
          "isZeta": false
        },
        {
          "isZeta": false
        },
        {
          "isZeta": true
        },
        {
          "isZeta": false
        }
      ],
      "gp": 20655,
      "relic": {
        "currentTier": 1
      }
    },
    {
      "defId": "IG86SENTINELDROID",
      "nameKey": "IG-86 Sentinel Droid",
      "rarity": 1,
      "level": 1,
      "gear": 1,
      "skills": [],
      "gp": 301,
      "relic": {
        "currentTier": 1
      }
    },
    {
      "defId": "SITHMARAUDER",
      "nameKey": "Sith Marauder",
      "rarity": 7,
      "level": 85,
      "gear": 13,
      "skills": [
        {
          "isZeta": false
        },
        {
          "isZeta": false
        },
        {
          "isZeta": false
        }
      ],
      "gp": 18172,
      "relic": {
        "currentTier": 6
      }
    },
    {
      "defId": "CAPITALMONCALAMARICRUISER",
      "nameKey": "Home One",
      "rarity": 6,
      "level": 85,
      "gear": 1,
      "skills": [
        {
          "isZeta": false
        },
        {
          "isZeta": false
        },
        {
          "isZeta": false
        },
        {
          "isZeta": false
        },
        {
          "isZeta": false
        }
      ],
      "gp": 32736
    },
    {
      "defId": "KYLOREN",
      "nameKey": "Kylo Ren",
      "rarity": 7,
      "level": 85,
      "gear": 8,
      "skills": [
        {
          "isZeta": false
        },
        {
          "isZeta": false
        },
        {
          "isZeta": true
        },
        {
          "isZeta": false
        }
      ],
      "gp": 13417,
      "relic": {
        "currentTier": 1
      }
    },
    {
      "defId": "SUNFAC",
      "nameKey": "Sun Fac",
      "rarity": 7,
      "level": 85,
      "gear": 12,
      "skills": [
        {
          "isZeta": false
        },
        {
          "isZeta": false
        },
        {
          "isZeta": false
        },
        {
          "isZeta": false
        }
      ],
      "gp": 17767,
      "relic": {
        "currentTier": 1
      }
    },
    {
      "defId": "DENGAR",
      "nameKey": "Dengar",
      "rarity": 7,
      "level": 85,
      "gear": 10,
      "skills": [
        {
          "isZeta": false
        },
        {
          "isZeta": false
        },
        {
          "isZeta": false
        },
        {
          "isZeta": false
        },
        {
          "isZeta": true
        },
        {
          "isZeta": false
        }
      ],
      "gp": 17343,
      "relic": {
        "currentTier": 1
      }
    },
    {
      "defId": "MAGNAGUARD",
      "nameKey": "IG-100 MagnaGuard",
      "rarity": 7,
      "level": 85,
      "gear": 12,
      "skills": [
        {
          "isZeta": false
        },
        {
          "isZeta": false
        },
        {
          "isZeta": true
        },
        {
          "isZeta": false
        }
      ],
      "gp": 17838,
      "relic": {
        "currentTier": 1
      }
    },
    {
      "defId": "TIESILENCER",
      "nameKey": "TIE Silencer",
      "rarity": 7,
      "level": 85,
      "gear": 1,
      "skills": [
        {
          "isZeta": false
        },
        {
          "isZeta": false
        },
        {
          "isZeta": false
        },
        {
          "isZeta": false
        }
      ],
      "gp": 53688
    },
    {
      "defId": "XWINGRED3",
      "nameKey": "Biggs Darklighter's X-wing",
      "rarity": 7,
      "level": 85,
      "gear": 1,
      "skills": [
        {
          "isZeta": false
        },
        {
          "isZeta": false
        },
        {
          "isZeta": false
        }
      ],
      "gp": 32134
    },
    {
      "defId": "CAPITALSTARDESTROYER",
      "nameKey": "Executrix",
      "rarity": 7,
      "level": 85,
      "gear": 1,
      "skills": [
        {
          "isZeta": false
        },
        {
          "isZeta": false
        },
        {
          "isZeta": false
        },
        {
          "isZeta": false
        },
        {
          "isZeta": false
        }
      ],
      "gp": 44596
    },
    {
      "defId": "QUIGONJINN",
      "nameKey": "Qui-Gon Jinn",
      "rarity": 5,
      "level": 80,
      "gear": 8,
      "skills": [
        {
          "isZeta": false
        },
        {
          "isZeta": false
        },
        {
          "isZeta": false
        },
        {
          "isZeta": true
        }
      ],
      "gp": 6577,
      "relic": {
        "currentTier": 1
      }
    },
    {
      "defId": "T3_M4",
      "nameKey": "T3-M4",
      "rarity": 7,
      "level": 62,
      "gear": 7,
      "skills": [
        {
          "isZeta": true
        },
        {
          "isZeta": false
        },
        {
          "isZeta": false
        },
        {
          "isZeta": false
        },
        {
          "isZeta": true
        }
      ],
      "gp": 7956,
      "relic": {
        "currentTier": 1
      }
    },
    {
      "defId": "ROYALGUARD",
      "nameKey": "Royal Guard",
      "rarity": 1,
      "level": 26,
      "gear": 3,
      "skills": [],
      "gp": 766,
      "relic": {
        "currentTier": 1
      }
    },
    {
      "defId": "BASTILASHAN",
      "nameKey": "Bastila Shan",
      "rarity": 7,
      "level": 85,
      "gear": 12,
      "skills": [
        {
          "isZeta": false
        },
        {
          "isZeta": false
        },
        {
          "isZeta": false
        },
        {
          "isZeta": true
        },
        {
          "isZeta": false
        },
        {
          "isZeta": false
        }
      ],
      "gp": 21508,
      "relic": {
        "currentTier": 1
      }
    },
    {
      "defId": "XWINGRED2",
      "nameKey": "Wedge Antilles's X-wing",
      "rarity": 5,
      "level": 85,
      "gear": 1,
      "skills": [
        {
          "isZeta": false
        },
        {
          "isZeta": false
        },
        {
          "isZeta": false
        }
      ],
      "gp": 15898
    },
    {
      "defId": "GEONOSIANSPY",
      "nameKey": "Geonosian Spy",
      "rarity": 7,
      "level": 85,
      "gear": 12,
      "skills": [
        {
          "isZeta": false
        },
        {
          "isZeta": false
        },
        {
          "isZeta": false
        },
        {
          "isZeta": false
        }
      ],
      "gp": 18210,
      "relic": {
        "currentTier": 1
      }
    },
    {
      "defId": "JEDISTARFIGHTERAHSOKATANO",
      "nameKey": "Ahsoka Tano's Jedi Starfighter",
      "rarity": 7,
      "level": 85,
      "gear": 1,
      "skills": [
        {
          "isZeta": false
        },
        {
          "isZeta": false
        },
        {
          "isZeta": false
        },
        {
          "isZeta": false
        }
      ],
      "gp": 52172
    },
    {
      "defId": "HOTHREBELSOLDIER",
      "nameKey": "Hoth Rebel Soldier",
      "rarity": 5,
      "level": 80,
      "gear": 8,
      "skills": [
        {
          "isZeta": false
        },
        {
          "isZeta": false
        },
        {
          "isZeta": false
        }
      ],
      "gp": 6301,
      "relic": {
        "currentTier": 1
      }
    },
    {
      "defId": "JAWA",
      "nameKey": "Jawa",
      "rarity": 3,
      "level": 1,
      "gear": 1,
      "skills": [],
      "gp": 676,
      "relic": {
        "currentTier": 1
      }
    },
    {
      "defId": "ASAJVENTRESS",
      "nameKey": "Asajj Ventress",
      "rarity": 7,
      "level": 85,
      "gear": 13,
      "skills": [
        {
          "isZeta": false
        },
        {
          "isZeta": false
        },
        {
          "isZeta": true
        },
        {
          "isZeta": true
        },
        {
          "isZeta": false
        }
      ],
      "gp": 21519,
      "relic": {
        "currentTier": 6
      }
    },
    {
      "defId": "POE",
      "nameKey": "Poe Dameron",
      "rarity": 5,
      "level": 80,
      "gear": 8,
      "skills": [
        {
          "isZeta": false
        },
        {
          "isZeta": false
        },
        {
          "isZeta": false
        },
        {
          "isZeta": false
        }
      ],
      "gp": 6577,
      "relic": {
        "currentTier": 1
      }
    },
    {
      "defId": "GRIEVOUS",
      "nameKey": "General Grievous",
      "rarity": 7,
      "level": 85,
      "gear": 13,
      "skills": [
        {
          "isZeta": false
        },
        {
          "isZeta": false
        },
        {
          "isZeta": false
        },
        {
          "isZeta": true
        },
        {
          "isZeta": true
        }
      ],
      "gp": 24358,
      "relic": {
        "currentTier": 6
      }
    },
    {
      "defId": "CHIRRUTIMWE",
      "nameKey": "Chirrut Îmwe",
      "rarity": 5,
      "level": 80,
      "gear": 8,
      "skills": [
        {
          "isZeta": false
        },
        {
          "isZeta": false
        },
        {
          "isZeta": false
        },
        {
          "isZeta": false
        },
        {
          "isZeta": false
        }
      ],
      "gp": 6853,
      "relic": {
        "currentTier": 1
      }
    },
    {
      "defId": "TALIA",
      "nameKey": "Talia",
      "rarity": 5,
      "level": 85,
      "gear": 8,
      "skills": [
        {
          "isZeta": false
        },
        {
          "isZeta": false
        },
        {
          "isZeta": false
        },
        {
          "isZeta": false
        }
      ],
      "gp": 10216,
      "relic": {
        "currentTier": 1
      }
    },
    {
      "defId": "JUHANI",
      "nameKey": "Juhani",
      "rarity": 7,
      "level": 85,
      "gear": 11,
      "skills": [
        {
          "isZeta": false
        },
        {
          "isZeta": false
        },
        {
          "isZeta": true
        },
        {
          "isZeta": false
        }
      ],
      "gp": 16894,
      "relic": {
        "currentTier": 1
      }
    },
    {
      "defId": "CAPITALNEGOTIATOR",
      "nameKey": "Negotiator",
      "rarity": 6,
      "level": 82,
      "gear": 1,
      "skills": [
        {
          "isZeta": false
        },
        {
          "isZeta": false
        },
        {
          "isZeta": false
        },
        {
          "isZeta": false
        },
        {
          "isZeta": false
        }
      ],
      "gp": 38791
    },
    {
      "defId": "KANANJARRUSS3",
      "nameKey": "Kanan Jarrus",
      "rarity": 7,
      "level": 85,
      "gear": 8,
      "skills": [
        {
          "isZeta": false
        },
        {
          "isZeta": true
        },
        {
          "isZeta": false
        },
        {
          "isZeta": false
        }
      ],
      "gp": 10276,
      "relic": {
        "currentTier": 1
      }
    },
    {
      "defId": "NIGHTSISTERZOMBIE",
      "nameKey": "Nightsister Zombie",
      "rarity": 7,
      "level": 85,
      "gear": 11,
      "skills": [
        {
          "isZeta": false
        },
        {
          "isZeta": false
        },
        {
          "isZeta": false
        },
        {
          "isZeta": false
        }
      ],
      "gp": 16963,
      "relic": {
        "currentTier": 1
      }
    },
    {
      "defId": "JEDISTARFIGHTERANAKIN",
      "nameKey": "Anakin's Eta-2 Starfighter",
      "rarity": 7,
      "level": 85,
      "gear": 1,
      "skills": [
        {
          "isZeta": false
        },
        {
          "isZeta": false
        },
        {
          "isZeta": false
        }
      ],
      "gp": 46606
    },
    {
      "defId": "JEDIKNIGHTCONSULAR",
      "nameKey": "Jedi Consular",
      "rarity": 7,
      "level": 85,
      "gear": 9,
      "skills": [
        {
          "isZeta": false
        },
        {
          "isZeta": false
        },
        {
          "isZeta": false
        }
      ],
      "gp": 13446,
      "relic": {
        "currentTier": 1
      }
    },
    {
      "defId": "AHSOKATANO",
      "nameKey": "Ahsoka Tano",
      "rarity": 7,
      "level": 85,
      "gear": 12,
      "skills": [
        {
          "isZeta": false
        },
        {
          "isZeta": false
        },
        {
          "isZeta": false
        },
        {
          "isZeta": true
        }
      ],
      "gp": 19939,
      "relic": {
        "currentTier": 1
      }
    },
    {
      "defId": "SABINEWRENS3",
      "nameKey": "Sabine Wren",
      "rarity": 5,
      "level": 80,
      "gear": 8,
      "skills": [
        {
          "isZeta": false
        },
        {
          "isZeta": true
        },
        {
          "isZeta": false
        },
        {
          "isZeta": false
        }
      ],
      "gp": 6820,
      "relic": {
        "currentTier": 1
      }
    },
    {
      "defId": "TIEFIGHTERIMPERIAL",
      "nameKey": "Imperial TIE Fighter",
      "rarity": 5,
      "level": 80,
      "gear": 1,
      "skills": [
        {
          "isZeta": false
        },
        {
          "isZeta": false
        },
        {
          "isZeta": false
        }
      ],
      "gp": 15445
    },
    {
      "defId": "PAPLOO",
      "nameKey": "Paploo",
      "rarity": 7,
      "level": 85,
      "gear": 10,
      "skills": [
        {
          "isZeta": false
        },
        {
          "isZeta": false
        },
        {
          "isZeta": false
        },
        {
          "isZeta": true
        }
      ],
      "gp": 15912,
      "relic": {
        "currentTier": 1
      }
    },
    {
      "defId": "STORMTROOPERHAN",
      "nameKey": "Stormtrooper Han",
      "rarity": 7,
      "level": 85,
      "gear": 8,
      "skills": [
        {
          "isZeta": false
        },
        {
          "isZeta": false
        },
        {
          "isZeta": true
        },
        {
          "isZeta": false
        }
      ],
      "gp": 13306,
      "relic": {
        "currentTier": 1
      }
    },
    {
      "defId": "EWOKELDER",
      "nameKey": "Ewok Elder",
      "rarity": 7,
      "level": 85,
      "gear": 12,
      "skills": [
        {
          "isZeta": false
        },
        {
          "isZeta": false
        },
        {
          "isZeta": false
        }
      ],
      "gp": 16588,
      "relic": {
        "currentTier": 1
      }
    },
    {
      "defId": "HERASYNDULLAS3",
      "nameKey": "Hera Syndulla",
      "rarity": 5,
      "level": 85,
      "gear": 8,
      "skills": [
        {
          "isZeta": false
        },
        {
          "isZeta": false
        },
        {
          "isZeta": false
        },
        {
          "isZeta": true
        }
      ],
      "gp": 7506,
      "relic": {
        "currentTier": 1
      }
    },
    {
      "defId": "BASTILASHANDARK",
      "nameKey": "Bastila Shan (Fallen)",
      "rarity": 7,
      "level": 85,
      "gear": 13,
      "skills": [
        {
          "isZeta": false
        },
        {
          "isZeta": false
        },
        {
          "isZeta": false
        },
        {
          "isZeta": false
        },
        {
          "isZeta": true
        },
        {
          "isZeta": false
        }
      ],
      "gp": 23013,
      "relic": {
        "currentTier": 9
      }
    },
    {
      "defId": "BOSSK",
      "nameKey": "Bossk",
      "rarity": 7,
      "level": 85,
      "gear": 13,
      "skills": [
        {
          "isZeta": true
        },
        {
          "isZeta": false
        },
        {
          "isZeta": false
        },
        {
          "isZeta": false
        },
        {
          "isZeta": true
        },
        {
          "isZeta": false
        }
      ],
      "gp": 22440,
      "relic": {
        "currentTier": 6
      }
    },
    {
      "defId": "CHIEFCHIRPA",
      "nameKey": "Chief Chirpa",
      "rarity": 7,
      "level": 85,
      "gear": 11,
      "skills": [
        {
          "isZeta": true
        },
        {
          "isZeta": false
        },
        {
          "isZeta": false
        },
        {
          "isZeta": false
        }
      ],
      "gp": 19602,
      "relic": {
        "currentTier": 1
      }
    },
    {
      "defId": "CT5555",
      "nameKey": "CT-5555 \"Fives\"",
      "rarity": 7,
      "level": 85,
      "gear": 9,
      "skills": [
        {
          "isZeta": false
        },
        {
          "isZeta": true
        },
        {
          "isZeta": true
        },
        {
          "isZeta": false
        },
        {
          "isZeta": false
        }
      ],
      "gp": 17325,
      "relic": {
        "currentTier": 1
      }
    },
    {
      "defId": "LUKESKYWALKER",
      "nameKey": "Luke Skywalker (Farmboy)",
      "rarity": 5,
      "level": 85,
      "gear": 8,
      "skills": [
        {
          "isZeta": false
        },
        {
          "isZeta": false
        },
        {
          "isZeta": true
        },
        {
          "isZeta": true
        }
      ],
      "gp": 9873,
      "relic": {
        "currentTier": 1
      }
    },
    {
      "defId": "FIRSTORDEREXECUTIONER",
      "nameKey": "First Order Executioner",
      "rarity": 7,
      "level": 85,
      "gear": 9,
      "skills": [
        {
          "isZeta": false
        },
        {
          "isZeta": false
        },
        {
          "isZeta": false
        }
      ],
      "gp": 13560,
      "relic": {
        "currentTier": 1
      }
    },
    {
      "defId": "VADER",
      "nameKey": "Darth Vader",
      "rarity": 7,
      "level": 85,
      "gear": 10,
      "skills": [
        {
          "isZeta": true
        },
        {
          "isZeta": false
        },
        {
          "isZeta": false
        },
        {
          "isZeta": false
        },
        {
          "isZeta": true
        },
        {
          "isZeta": true
        }
      ],
      "gp": 15853,
      "relic": {
        "currentTier": 1
      }
    },
    {
      "defId": "COUNTDOOKU",
      "nameKey": "Count Dooku",
      "rarity": 7,
      "level": 85,
      "gear": 10,
      "skills": [
        {
          "isZeta": false
        },
        {
          "isZeta": true
        },
        {
          "isZeta": false
        },
        {
          "isZeta": false
        },
        {
          "isZeta": false
        }
      ],
      "gp": 15970,
      "relic": {
        "currentTier": 1
      }
    },
    {
      "defId": "MISSIONVAO",
      "nameKey": "Mission Vao",
      "rarity": 7,
      "level": 85,
      "gear": 11,
      "skills": [
        {
          "isZeta": true
        },
        {
          "isZeta": false
        },
        {
          "isZeta": false
        },
        {
          "isZeta": false
        }
      ],
      "gp": 19311,
      "relic": {
        "currentTier": 1
      }
    },
    {
      "defId": "ARC170CLONESERGEANT",
      "nameKey": "Clone Sergeant's ARC-170",
      "rarity": 6,
      "level": 85,
      "gear": 1,
      "skills": [
        {
          "isZeta": false
        },
        {
          "isZeta": false
        },
        {
          "isZeta": false
        },
        {
          "isZeta": false
        }
      ],
      "gp": 32701
    },
    {
      "defId": "HOUNDSTOOTH",
      "nameKey": "Hound's Tooth",
      "rarity": 7,
      "level": 85,
      "gear": 1,
      "skills": [
        {
          "isZeta": false
        },
        {
          "isZeta": false
        },
        {
          "isZeta": false
        },
        {
          "isZeta": false
        }
      ],
      "gp": 57799
    },
    {
      "defId": "GEONOSIANBROODALPHA",
      "nameKey": "Geonosian Brood Alpha",
      "rarity": 7,
      "level": 85,
      "gear": 12,
      "skills": [
        {
          "isZeta": false
        },
        {
          "isZeta": false
        },
        {
          "isZeta": false
        },
        {
          "isZeta": false
        },
        {
          "isZeta": true
        },
        {
          "isZeta": true
        }
      ],
      "gp": 24426,
      "relic": {
        "currentTier": 1
      }
    },
    {
      "defId": "ADMINISTRATORLANDO",
      "nameKey": "Lando Calrissian",
      "rarity": 5,
      "level": 80,
      "gear": 8,
      "skills": [
        {
          "isZeta": false
        },
        {
          "isZeta": false
        },
        {
          "isZeta": false
        },
        {
          "isZeta": false
        }
      ],
      "gp": 6577,
      "relic": {
        "currentTier": 1
      }
    },
    {
      "defId": "ANAKINKNIGHT",
      "nameKey": "Jedi Knight Anakin",
      "rarity": 7,
      "level": 85,
      "gear": 13,
      "skills": [
        {
          "isZeta": false
        },
        {
          "isZeta": true
        },
        {
          "isZeta": false
        },
        {
          "isZeta": false
        }
      ],
      "gp": 18790,
      "relic": {
        "currentTier": 5
      }
    },
    {
      "defId": "MAUL",
      "nameKey": "Darth Maul",
      "rarity": 5,
      "level": 80,
      "gear": 8,
      "skills": [
        {
          "isZeta": false
        },
        {
          "isZeta": false
        },
        {
          "isZeta": false
        },
        {
          "isZeta": true
        }
      ],
      "gp": 6577,
      "relic": {
        "currentTier": 1
      }
    },
    {
      "defId": "JOLEEBINDO",
      "nameKey": "Jolee Bindo",
      "rarity": 7,
      "level": 85,
      "gear": 13,
      "skills": [
        {
          "isZeta": false
        },
        {
          "isZeta": false
        },
        {
          "isZeta": true
        },
        {
          "isZeta": false
        },
        {
          "isZeta": false
        }
      ],
      "gp": 21751,
      "relic": {
        "currentTier": 6
      }
    },
    {
      "defId": "IG2000",
      "nameKey": "IG-2000",
      "rarity": 6,
      "level": 85,
      "gear": 1,
      "skills": [
        {
          "isZeta": false
        },
        {
          "isZeta": false
        },
        {
          "isZeta": false
        },
        {
          "isZeta": false
        }
      ],
      "gp": 43109
    },
    {
      "defId": "NIGHTSISTERSPIRIT",
      "nameKey": "Nightsister Spirit",
      "rarity": 7,
      "level": 85,
      "gear": 12,
      "skills": [
        {
          "isZeta": false
        },
        {
          "isZeta": false
        },
        {
          "isZeta": false
        }
      ],
      "gp": 16797,
      "relic": {
        "currentTier": 1
      }
    },
    {
      "defId": "XANADUBLOOD",
      "nameKey": "Xanadu Blood",
      "rarity": 7,
      "level": 85,
      "gear": 1,
      "skills": [
        {
          "isZeta": false
        },
        {
          "isZeta": false
        },
        {
          "isZeta": false
        },
        {
          "isZeta": false
        }
      ],
      "gp": 46101
    },
    {
      "defId": "FIRSTORDERTIEPILOT",
      "nameKey": "First Order TIE Pilot",
      "rarity": 1,
      "level": 1,
      "gear": 1,
      "skills": [],
      "gp": 301,
      "relic": {
        "currentTier": 1
      }
    },
    {
      "defId": "DARTHSION",
      "nameKey": "Darth Sion",
      "rarity": 7,
      "level": 85,
      "gear": 9,
      "skills": [
        {
          "isZeta": false
        },
        {
          "isZeta": false
        },
        {
          "isZeta": false
        },
        {
          "isZeta": false
        },
        {
          "isZeta": true
        }
      ],
      "gp": 15694,
      "relic": {
        "currentTier": 1
      }
    },
    {
      "defId": "CLONESERGEANTPHASEI",
      "nameKey": "Clone Sergeant - Phase I",
      "rarity": 7,
      "level": 85,
      "gear": 8,
      "skills": [
        {
          "isZeta": false
        },
        {
          "isZeta": false
        },
        {
          "isZeta": false
        }
      ],
      "gp": 12846,
      "relic": {
        "currentTier": 1
      }
    },
    {
      "defId": "CAPITALJEDICRUISER",
      "nameKey": "Endurance",
      "rarity": 6,
      "level": 80,
      "gear": 1,
      "skills": [
        {
          "isZeta": false
        },
        {
          "isZeta": false
        },
        {
          "isZeta": false
        },
        {
          "isZeta": false
        },
        {
          "isZeta": false
        }
      ],
      "gp": 21409
    },
    {
      "defId": "ADMIRALACKBAR",
      "nameKey": "Admiral Ackbar",
      "rarity": 7,
      "level": 85,
      "gear": 9,
      "skills": [
        {
          "isZeta": false
        },
        {
          "isZeta": false
        },
        {
          "isZeta": false
        },
        {
          "isZeta": false
        }
      ],
      "gp": 13975,
      "relic": {
        "currentTier": 1
      }
    },
    {
      "defId": "FIRSTORDERTROOPER",
      "nameKey": "First Order Stormtrooper",
      "rarity": 7,
      "level": 85,
      "gear": 8,
      "skills": [
        {
          "isZeta": false
        },
        {
          "isZeta": false
        },
        {
          "isZeta": true
        }
      ],
      "gp": 12918,
      "relic": {
        "currentTier": 1
      }
    },
    {
      "defId": "PHANTOM2",
      "nameKey": "Phantom II",
      "rarity": 6,
      "level": 85,
      "gear": 1,
      "skills": [
        {
          "isZeta": false
        },
        {
          "isZeta": false
        },
        {
          "isZeta": false
        },
        {
          "isZeta": false
        },
        {
          "isZeta": false
        },
        {
          "isZeta": false
        }
      ],
      "gp": 27163
    },
    {
      "defId": "GREEDO",
      "nameKey": "Greedo",
      "rarity": 5,
      "level": 80,
      "gear": 8,
      "skills": [
        {
          "isZeta": false
        },
        {
          "isZeta": false
        },
        {
          "isZeta": true
        },
        {
          "isZeta": false
        },
        {
          "isZeta": false
        },
        {
          "isZeta": false
        }
      ],
      "gp": 7881,
      "relic": {
        "currentTier": 1
      }
    },
    {
      "defId": "STORMTROOPER",
      "nameKey": "Stormtrooper",
      "rarity": 5,
      "level": 80,
      "gear": 8,
      "skills": [
        {
          "isZeta": false
        },
        {
          "isZeta": false
        },
        {
          "isZeta": true
        }
      ],
      "gp": 6301,
      "relic": {
        "currentTier": 1
      }
    },
    {
      "defId": "JANGOFETT",
      "nameKey": "Jango Fett",
      "rarity": 7,
      "level": 1,
      "gear": 1,
      "skills": [],
      "gp": 4656,
      "relic": {
        "currentTier": 1
      }
    },
    {
      "defId": "CHOPPERS3",
      "nameKey": "Chopper",
      "rarity": 7,
      "level": 85,
      "gear": 8,
      "skills": [
        {
          "isZeta": false
        },
        {
          "isZeta": false
        },
        {
          "isZeta": false
        },
        {
          "isZeta": false
        }
      ],
      "gp": 10398,
      "relic": {
        "currentTier": 1
      }
    },
    {
      "defId": "HOTHREBELSCOUT",
      "nameKey": "Hoth Rebel Scout",
      "rarity": 5,
      "level": 80,
      "gear": 8,
      "skills": [
        {
          "isZeta": false
        },
        {
          "isZeta": false
        },
        {
          "isZeta": false
        }
      ],
      "gp": 6301,
      "relic": {
        "currentTier": 1
      }
    },
    {
      "defId": "BOBAFETT",
      "nameKey": "Boba Fett",
      "rarity": 7,
      "level": 85,
      "gear": 12,
      "skills": [
        {
          "isZeta": false
        },
        {
          "isZeta": false
        },
        {
          "isZeta": true
        },
        {
          "isZeta": false
        },
        {
          "isZeta": false
        },
        {
          "isZeta": false
        }
      ],
      "gp": 21390,
      "relic": {
        "currentTier": 1
      }
    },
    {
      "defId": "GHOST",
      "nameKey": "Ghost",
      "rarity": 5,
      "level": 85,
      "gear": 1,
      "skills": [
        {
          "isZeta": false
        },
        {
          "isZeta": false
        },
        {
          "isZeta": false
        },
        {
          "isZeta": false
        },
        {
          "isZeta": false
        },
        {
          "isZeta": false
        }
      ],
      "gp": 26143
    },
    {
      "defId": "NUTEGUNRAY",
      "nameKey": "Nute Gunray",
      "rarity": 7,
      "level": 85,
      "gear": 12,
      "skills": [
        {
          "isZeta": false
        },
        {
          "isZeta": false
        },
        {
          "isZeta": false
        },
        {
          "isZeta": false
        },
        {
          "isZeta": true
        }
      ],
      "gp": 20911,
      "relic": {
        "currentTier": 1
      }
    },
    {
      "defId": "WATTAMBOR",
      "nameKey": "Wat Tambor",
      "rarity": 5,
      "level": 85,
      "gear": 11,
      "skills": [
        {
          "isZeta": true
        },
        {
          "isZeta": false
        },
        {
          "isZeta": false
        },
        {
          "isZeta": false
        }
      ],
      "gp": 16002,
      "relic": {
        "currentTier": 1
      }
    },
    {
      "defId": "WEDGEANTILLES",
      "nameKey": "Wedge Antilles",
      "rarity": 5,
      "level": 80,
      "gear": 8,
      "skills": [
        {
          "isZeta": false
        },
        {
          "isZeta": false
        },
        {
          "isZeta": false
        },
        {
          "isZeta": false
        }
      ],
      "gp": 6820,
      "relic": {
        "currentTier": 1
      }
    },
    {
      "defId": "SLAVE1",
      "nameKey": "Slave I",
      "rarity": 7,
      "level": 85,
      "gear": 1,
      "skills": [
        {
          "isZeta": false
        },
        {
          "isZeta": false
        },
        {
          "isZeta": false
        },
        {
          "isZeta": false
        }
      ],
      "gp": 55227
    },
    {
      "defId": "VEERS",
      "nameKey": "General Veers",
      "rarity": 5,
      "level": 80,
      "gear": 8,
      "skills": [
        {
          "isZeta": false
        },
        {
          "isZeta": false
        },
        {
          "isZeta": true
        },
        {
          "isZeta": false
        }
      ],
      "gp": 6577,
      "relic": {
        "currentTier": 1
      }
    },
    {
      "defId": "DEATHTROOPER",
      "nameKey": "Death Trooper",
      "rarity": 5,
      "level": 80,
      "gear": 8,
      "skills": [
        {
          "isZeta": false
        },
        {
          "isZeta": false
        },
        {
          "isZeta": true
        },
        {
          "isZeta": false
        }
      ],
      "gp": 6577,
      "relic": {
        "currentTier": 1
      }
    },
    {
      "defId": "CARTHONASI",
      "nameKey": "Carth Onasi",
      "rarity": 7,
      "level": 85,
      "gear": 11,
      "skills": [
        {
          "isZeta": true
        },
        {
          "isZeta": false
        },
        {
          "isZeta": false
        },
        {
          "isZeta": false
        }
      ],
      "gp": 18867,
      "relic": {
        "currentTier": 1
      }
    },
    {
      "defId": "ARCTROOPER501ST",
      "nameKey": "ARC Trooper",
      "rarity": 7,
      "level": 85,
      "gear": 9,
      "skills": [
        {
          "isZeta": false
        },
        {
          "isZeta": true
        },
        {
          "isZeta": false
        }
      ],
      "gp": 14194,
      "relic": {
        "currentTier": 1
      }
    },
    {
      "defId": "WICKET",
      "nameKey": "Wicket",
      "rarity": 7,
      "level": 85,
      "gear": 11,
      "skills": [
        {
          "isZeta": false
        },
        {
          "isZeta": false
        },
        {
          "isZeta": false
        },
        {
          "isZeta": true
        }
      ],
      "gp": 19486,
      "relic": {
        "currentTier": 1
      }
    },
    {
      "defId": "GEONOSIANSTARFIGHTER2",
      "nameKey": "Geonosian Soldier's Starfighter",
      "rarity": 7,
      "level": 85,
      "gear": 1,
      "skills": [
        {
          "isZeta": false
        },
        {
          "isZeta": false
        },
        {
          "isZeta": false
        },
        {
          "isZeta": false
        }
      ],
      "gp": 45413
    },
    {
      "defId": "GEONOSIANSTARFIGHTER1",
      "nameKey": "Sun Fac's Geonosian Starfighter",
      "rarity": 6,
      "level": 1,
      "gear": 1,
      "skills": [
        {
          "isZeta": false
        }
      ],
      "gp": 36553
    },
    {
      "defId": "GEONOSIANSTARFIGHTER3",
      "nameKey": "Geonosian Spy's Starfighter",
      "rarity": 7,
      "level": 85,
      "gear": 1,
      "skills": [
        {
          "isZeta": false
        },
        {
          "isZeta": false
        },
        {
          "isZeta": false
        }
      ],
      "gp": 45301
    },
    {
      "defId": "MACEWINDU",
      "nameKey": "Mace Windu",
      "rarity": 7,
      "level": 80,
      "gear": 8,
      "skills": [
        {
          "isZeta": false
        },
        {
          "isZeta": false
        },
        {
          "isZeta": false
        },
        {
          "isZeta": false
        }
      ],
      "gp": 9712,
      "relic": {
        "currentTier": 1
      }
    },
    {
      "defId": "DATHCHA",
      "nameKey": "Dathcha",
      "rarity": 4,
      "level": 1,
      "gear": 1,
      "skills": [],
      "gp": 1014,
      "relic": {
        "currentTier": 1
      }
    },
    {
      "defId": "JYNERSO",
      "nameKey": "Jyn Erso",
      "rarity": 5,
      "level": 80,
      "gear": 8,
      "skills": [
        {
          "isZeta": false
        },
        {
          "isZeta": false
        },
        {
          "isZeta": true
        },
        {
          "isZeta": false
        },
        {
          "isZeta": true
        }
      ],
      "gp": 6853,
      "relic": {
        "currentTier": 1
      }
    },
    {
      "defId": "IG88",
      "nameKey": "IG-88",
      "rarity": 7,
      "level": 85,
      "gear": 11,
      "skills": [
        {
          "isZeta": false
        },
        {
          "isZeta": true
        },
        {
          "isZeta": false
        },
        {
          "isZeta": false
        },
        {
          "isZeta": false
        }
      ],
      "gp": 17679,
      "relic": {
        "currentTier": 1
      }
    },
    {
      "defId": "TEEBO",
      "nameKey": "Teebo",
      "rarity": 2,
      "level": 1,
      "gear": 1,
      "skills": [],
      "gp": 451,
      "relic": {
        "currentTier": 1
      }
    },
    {
      "defId": "REY",
      "nameKey": "Rey (Scavenger)",
      "rarity": 5,
      "level": 80,
      "gear": 8,
      "skills": [
        {
          "isZeta": true
        },
        {
          "isZeta": false
        },
        {
          "isZeta": false
        },
        {
          "isZeta": false
        }
      ],
      "gp": 6577,
      "relic": {
        "currentTier": 1
      }
    },
    {
      "defId": "BLADEOFDORIN",
      "nameKey": "Plo Koon's Jedi Starfighter",
      "rarity": 5,
      "level": 85,
      "gear": 1,
      "skills": [
        {
          "isZeta": false
        },
        {
          "isZeta": false
        },
        {
          "isZeta": false
        }
      ],
      "gp": 11514
    },
    {
      "defId": "DARTHNIHILUS",
      "nameKey": "Darth Nihilus",
      "rarity": 7,
      "level": 85,
      "gear": 12,
      "skills": [
        {
          "isZeta": true
        },
        {
          "isZeta": false
        },
        {
          "isZeta": true
        },
        {
          "isZeta": false
        },
        {
          "isZeta": false
        }
      ],
      "gp": 18550,
      "relic": {
        "currentTier": 1
      }
    },
    {
      "defId": "EMPERORPALPATINE",
      "nameKey": "Emperor Palpatine",
      "rarity": 7,
      "level": 85,
      "gear": 9,
      "skills": [
        {
          "isZeta": true
        },
        {
          "isZeta": false
        },
        {
          "isZeta": false
        },
        {
          "isZeta": false
        },
        {
          "isZeta": true
        }
      ],
      "gp": 14475,
      "relic": {
        "currentTier": 1
      }
    },
    {
      "defId": "PLOKOON",
      "nameKey": "Plo Koon",
      "rarity": 6,
      "level": 1,
      "gear": 1,
      "skills": [],
      "gp": 2661,
      "relic": {
        "currentTier": 1
      }
    },
    {
      "defId": "SITHBOMBER",
      "nameKey": "B-28 Extinction-class Bomber",
      "rarity": 5,
      "level": 85,
      "gear": 1,
      "skills": [
        {
          "isZeta": false
        },
        {
          "isZeta": false
        },
        {
          "isZeta": false
        },
        {
          "isZeta": false
        }
      ],
      "gp": 40962
    },
    {
      "defId": "DAKA",
      "nameKey": "Old Daka",
      "rarity": 7,
      "level": 85,
      "gear": 12,
      "skills": [
        {
          "isZeta": false
        },
        {
          "isZeta": false
        },
        {
          "isZeta": false
        },
        {
          "isZeta": true
        }
      ],
      "gp": 20058,
      "relic": {
        "currentTier": 1
      }
    },
    {
      "defId": "GRANDMOFFTARKIN",
      "nameKey": "Grand Moff Tarkin",
      "rarity": 7,
      "level": 85,
      "gear": 12,
      "skills": [
        {
          "isZeta": true
        },
        {
          "isZeta": false
        },
        {
          "isZeta": true
        },
        {
          "isZeta": false
        },
        {
          "isZeta": false
        }
      ],
      "gp": 17199,
      "relic": {
        "currentTier": 1
      }
    },
    {
      "defId": "LOGRAY",
      "nameKey": "Logray",
      "rarity": 7,
      "level": 85,
      "gear": 9,
      "skills": [
        {
          "isZeta": false
        },
        {
          "isZeta": false
        },
        {
          "isZeta": false
        },
        {
          "isZeta": true
        }
      ],
      "gp": 15025,
      "relic": {
        "currentTier": 1
      }
    },
    {
      "defId": "URORRURRR",
      "nameKey": "URoRRuR'R'R",
      "rarity": 4,
      "level": 1,
      "gear": 1,
      "skills": [],
      "gp": 1014,
      "relic": {
        "currentTier": 1
      }
    },
    {
      "defId": "GEONOSIANSOLDIER",
      "nameKey": "Geonosian Soldier",
      "rarity": 7,
      "level": 85,
      "gear": 12,
      "skills": [
        {
          "isZeta": false
        },
        {
          "isZeta": false
        },
        {
          "isZeta": false
        }
      ],
      "gp": 16935,
      "relic": {
        "currentTier": 1
      }
    },
    {
      "defId": "SNOWTROOPER",
      "nameKey": "Snowtrooper",
      "rarity": 5,
      "level": 80,
      "gear": 8,
      "skills": [
        {
          "isZeta": false
        },
        {
          "isZeta": false
        },
        {
          "isZeta": false
        }
      ],
      "gp": 6301,
      "relic": {
        "currentTier": 1
      }
    },
    {
      "defId": "SHORETROOPER",
      "nameKey": "Shoretrooper",
      "rarity": 5,
      "level": 80,
      "gear": 8,
      "skills": [
        {
          "isZeta": false
        },
        {
          "isZeta": false
        },
        {
          "isZeta": false
        }
      ],
      "gp": 6301,
      "relic": {
        "currentTier": 1
      }
    },
    {
      "defId": "PRINCESSLEIA",
      "nameKey": "Princess Leia",
      "rarity": 5,
      "level": 80,
      "gear": 8,
      "skills": [
        {
          "isZeta": false
        },
        {
          "isZeta": false
        },
        {
          "isZeta": false
        },
        {
          "isZeta": true
        }
      ],
      "gp": 6577,
      "relic": {
        "currentTier": 1
      }
    },
    {
      "defId": "VULTUREDROID",
      "nameKey": "Vulture Droid",
      "rarity": 5,
      "level": 80,
      "gear": 1,
      "skills": [
        {
          "isZeta": false
        },
        {
          "isZeta": false
        },
        {
          "isZeta": false
        },
        {
          "isZeta": false
        }
      ],
      "gp": 3796
    },
    {
      "defId": "DARTHMALAK",
      "nameKey": "Darth Malak",
      "rarity": 7,
      "level": 85,
      "gear": 13,
      "skills": [
        {
          "isZeta": false
        },
        {
          "isZeta": false
        },
        {
          "isZeta": false
        },
        {
          "isZeta": true
        },
        {
          "isZeta": true
        }
      ],
      "gp": 24087,
      "relic": {
        "currentTier": 9
      }
    },
    {
      "defId": "RESISTANCETROOPER",
      "nameKey": "Resistance Trooper",
      "rarity": 5,
      "level": 80,
      "gear": 8,
      "skills": [
        {
          "isZeta": false
        },
        {
          "isZeta": false
        },
        {
          "isZeta": false
        }
      ],
      "gp": 6301,
      "relic": {
        "currentTier": 1
      }
    },
    {
      "defId": "FINN",
      "nameKey": "Finn",
      "rarity": 5,
      "level": 80,
      "gear": 8,
      "skills": [
        {
          "isZeta": true
        },
        {
          "isZeta": false
        },
        {
          "isZeta": false
        },
        {
          "isZeta": false
        }
      ],
      "gp": 6577,
      "relic": {
        "currentTier": 1
      }
    },
    {
      "defId": "PHASMA",
      "nameKey": "Captain Phasma",
      "rarity": 5,
      "level": 80,
      "gear": 8,
      "skills": [
        {
          "isZeta": false
        },
        {
          "isZeta": false
        },
        {
          "isZeta": true
        },
        {
          "isZeta": false
        }
      ],
      "gp": 6577,
      "relic": {
        "currentTier": 1
      }
    },
    {
      "defId": "HK47",
      "nameKey": "HK-47",
      "rarity": 7,
      "level": 85,
      "gear": 13,
      "skills": [
        {
          "isZeta": true
        },
        {
          "isZeta": false
        },
        {
          "isZeta": false
        },
        {
          "isZeta": false
        },
        {
          "isZeta": false
        },
        {
          "isZeta": true
        }
      ],
      "gp": 24933,
      "relic": {
        "currentTier": 9
      }
    },
    {
      "defId": "TUSKENRAIDER",
      "nameKey": "Tusken Raider",
      "rarity": 3,
      "level": 1,
      "gear": 1,
      "skills": [],
      "gp": 676,
      "relic": {
        "currentTier": 1
      }
    },
    {
      "defId": "CASSIANANDOR",
      "nameKey": "Cassian Andor",
      "rarity": 5,
      "level": 80,
      "gear": 8,
      "skills": [
        {
          "isZeta": false
        },
        {
          "isZeta": true
        },
        {
          "isZeta": false
        },
        {
          "isZeta": false
        }
      ],
      "gp": 6577,
      "relic": {
        "currentTier": 1
      }
    },
    {
      "defId": "EZRABRIDGERS3",
      "nameKey": "Ezra Bridger",
      "rarity": 5,
      "level": 85,
      "gear": 8,
      "skills": [
        {
          "isZeta": false
        },
        {
          "isZeta": false
        },
        {
          "isZeta": true
        },
        {
          "isZeta": false
        }
      ],
      "gp": 7627,
      "relic": {
        "currentTier": 1
      }
    },
    {
      "defId": "DARTHTRAYA",
      "nameKey": "Darth Traya",
      "rarity": 7,
      "level": 85,
      "gear": 11,
      "skills": [
        {
          "isZeta": false
        },
        {
          "isZeta": false
        },
        {
          "isZeta": false
        },
        {
          "isZeta": true
        },
        {
          "isZeta": true
        }
      ],
      "gp": 17434,
      "relic": {
        "currentTier": 1
      }
    },
    {
      "defId": "BAZEMALBUS",
      "nameKey": "Baze Malbus",
      "rarity": 5,
      "level": 80,
      "gear": 8,
      "skills": [
        {
          "isZeta": false
        },
        {
          "isZeta": false
        },
        {
          "isZeta": false
        },
        {
          "isZeta": false
        },
        {
          "isZeta": false
        }
      ],
      "gp": 6853,
      "relic": {
        "currentTier": 1
      }
    },
    {
      "defId": "ZAALBAR",
      "nameKey": "Zaalbar",
      "rarity": 7,
      "level": 85,
      "gear": 11,
      "skills": [
        {
          "isZeta": false
        },
        {
          "isZeta": false
        },
        {
          "isZeta": false
        },
        {
          "isZeta": true
        }
      ],
      "gp": 19438,
      "relic": {
        "currentTier": 1
      }
    },
    {
      "defId": "CLONEWARSCHEWBACCA",
      "nameKey": "Clone Wars Chewbacca",
      "rarity": 3,
      "level": 30,
      "gear": 3,
      "skills": [],
      "gp": 1207,
      "relic": {
        "currentTier": 1
      }
    },
    {
      "defId": "JEDISTARFIGHTERCONSULAR",
      "nameKey": "Jedi Consular's Starfighter",
      "rarity": 7,
      "level": 85,
      "gear": 1,
      "skills": [
        {
          "isZeta": false
        },
        {
          "isZeta": false
        },
        {
          "isZeta": false
        },
        {
          "isZeta": false
        }
      ],
      "gp": 37054
    },
    {
      "defId": "FIRSTORDEROFFICERMALE",
      "nameKey": "First Order Officer",
      "rarity": 7,
      "level": 85,
      "gear": 11,
      "skills": [
        {
          "isZeta": false
        },
        {
          "isZeta": false
        },
        {
          "isZeta": false
        }
      ],
      "gp": 15445,
      "relic": {
        "currentTier": 1
      }
    },
    {
      "defId": "B2SUPERBATTLEDROID",
      "nameKey": "B2 Super Battle Droid",
      "rarity": 7,
      "level": 85,
      "gear": 12,
      "skills": [
        {
          "isZeta": false
        },
        {
          "isZeta": false
        },
        {
          "isZeta": false
        },
        {
          "isZeta": true
        }
      ],
      "gp": 20568,
      "relic": {
        "currentTier": 1
      }
    },
    {
      "defId": "DARTHSIDIOUS",
      "nameKey": "Darth Sidious",
      "rarity": 5,
      "level": 80,
      "gear": 8,
      "skills": [
        {
          "isZeta": true
        },
        {
          "isZeta": false
        },
        {
          "isZeta": false
        },
        {
          "isZeta": false
        }
      ],
      "gp": 6699,
      "relic": {
        "currentTier": 1
      }
    },
    {
      "defId": "OLDBENKENOBI",
      "nameKey": "Obi-Wan Kenobi (Old Ben)",
      "rarity": 7,
      "level": 85,
      "gear": 9,
      "skills": [
        {
          "isZeta": false
        },
        {
          "isZeta": false
        },
        {
          "isZeta": true
        },
        {
          "isZeta": false
        },
        {
          "isZeta": true
        }
      ],
      "gp": 14034,
      "relic": {
        "currentTier": 1
      }
    },
    {
      "defId": "KYLORENUNMASKED",
      "nameKey": "Kylo Ren (Unmasked)",
      "rarity": 7,
      "level": 85,
      "gear": 13,
      "skills": [
        {
          "isZeta": false
        },
        {
          "isZeta": true
        },
        {
          "isZeta": false
        },
        {
          "isZeta": false
        },
        {
          "isZeta": true
        }
      ],
      "gp": 21540,
      "relic": {
        "currentTier": 6
      }
    },
    {
      "defId": "RESISTANCEPILOT",
      "nameKey": "Resistance Pilot",
      "rarity": 5,
      "level": 80,
      "gear": 8,
      "skills": [
        {
          "isZeta": false
        },
        {
          "isZeta": false
        },
        {
          "isZeta": false
        }
      ],
      "gp": 6301,
      "relic": {
        "currentTier": 1
      }
    },
    {
      "defId": "JEDIKNIGHTGUARDIAN",
      "nameKey": "Jedi Knight Guardian",
      "rarity": 2,
      "level": 1,
      "gear": 1,
      "skills": [],
      "gp": 451,
      "relic": {
        "currentTier": 1
      }
    },
    {
      "defId": "CANDEROUSORDO",
      "nameKey": "Canderous Ordo",
      "rarity": 7,
      "level": 85,
      "gear": 11,
      "skills": [
        {
          "isZeta": true
        },
        {
          "isZeta": false
        },
        {
          "isZeta": false
        },
        {
          "isZeta": false
        }
      ],
      "gp": 19602,
      "relic": {
        "currentTier": 1
      }
    },
    {
      "defId": "HANSOLO",
      "nameKey": "Han Solo",
      "rarity": 7,
      "level": 1,
      "gear": 1,
      "skills": [],
      "gp": 4656,
      "relic": {
        "currentTier": 1
      }
    },
    {
      "defId": "SMUGGLERHAN",
      "nameKey": "Veteran Smuggler Han Solo",
      "rarity": 5,
      "level": 80,
      "gear": 8,
      "skills": [
        {
          "isZeta": false
        },
        {
          "isZeta": false
        },
        {
          "isZeta": true
        },
        {
          "isZeta": false
        }
      ],
      "gp": 6577,
      "relic": {
        "currentTier": 1
      }
    },
    {
      "defId": "CADBANE",
      "nameKey": "Cad Bane",
      "rarity": 7,
      "level": 85,
      "gear": 11,
      "skills": [
        {
          "isZeta": false
        },
        {
          "isZeta": false
        },
        {
          "isZeta": false
        },
        {
          "isZeta": false
        },
        {
          "isZeta": false
        }
      ],
      "gp": 18168,
      "relic": {
        "currentTier": 1
      }
    },
    {
      "defId": "UGNAUGHT",
      "nameKey": "Ugnaught",
      "rarity": 2,
      "level": 54,
      "gear": 6,
      "skills": [],
      "gp": 2098,
      "relic": {
        "currentTier": 1
      }
    },
    {
      "defId": "TIEFIGHTERPILOT",
      "nameKey": "TIE Fighter Pilot",
      "rarity": 5,
      "level": 80,
      "gear": 8,
      "skills": [
        {
          "isZeta": false
        },
        {
          "isZeta": false
        },
        {
          "isZeta": false
        }
      ],
      "gp": 6909,
      "relic": {
        "currentTier": 1
      }
    },
    {
      "defId": "GRANDMASTERYODA",
      "nameKey": "Grand Master Yoda",
      "rarity": 7,
      "level": 85,
      "gear": 13,
      "skills": [
        {
          "isZeta": false
        },
        {
          "isZeta": false
        },
        {
          "isZeta": false
        },
        {
          "isZeta": true
        },
        {
          "isZeta": true
        }
      ],
      "gp": 19341,
      "relic": {
        "currentTier": 6
      }
    },
    {
      "defId": "UMBARANSTARFIGHTER",
      "nameKey": "Umbaran Starfighter",
      "rarity": 7,
      "level": 85,
      "gear": 1,
      "skills": [
        {
          "isZeta": false
        },
        {
          "isZeta": false
        },
        {
          "isZeta": false
        },
        {
          "isZeta": false
        }
      ],
      "gp": 45782
    },
    {
      "defId": "SMUGGLERCHEWBACCA",
      "nameKey": "Veteran Smuggler Chewbacca",
      "rarity": 5,
      "level": 80,
      "gear": 8,
      "skills": [
        {
          "isZeta": true
        },
        {
          "isZeta": false
        },
        {
          "isZeta": false
        },
        {
          "isZeta": false
        }
      ],
      "gp": 6577,
      "relic": {
        "currentTier": 1
      }
    },
    {
      "defId": "SHAAKTI",
      "nameKey": "Shaak Ti",
      "rarity": 7,
      "level": 85,
      "gear": 11,
      "skills": [
        {
          "isZeta": false
        },
        {
          "isZeta": false
        },
        {
          "isZeta": false
        },
        {
          "isZeta": true
        },
        {
          "isZeta": true
        }
      ],
      "gp": 19780,
      "relic": {
        "currentTier": 1
      }
    }
  ]
}